{
    "title": "RFP: R RFP: R RFP: R RFP: Reeeequest f quest f quest f quest foooor Pr r Pr r Pr r Proposal oposal oposal oposal",
    "outline": [
        {
            "level": "H3",
            "text": "Ontario’s Libraries Working Together",
            "page": 1
        },
        {
            "level": "H1",
            "text": "To Present a Proposal for Developing the Business Plan for the Ontario Digital Library",
            "page": 1
        },
        {
            "level": "H2",
            "text": "March 21, 2003",
            "page": 1
        },
        {
            "level": "H2",
            "text": "Ontario’s Digital Library",
            "page": 2
        },
        {
            "level": "H3",
            "text": "A Critical Component for Implementing Ontario’s Road Map to Prosperity Strategy",
            "page": 2
        }
    ]
}